nmlang-0.1.0.dist-info/licenses/LICENSE
numerus/__init__.py
numerus/_core.py
numerus/cli.py
nmlang-0.1.0.dist-info/METADATA
nmlang-0.1.0.dist-info/WHEEL
nmlang-0.1.0.dist-info/entry_points.txt
nmlang-0.1.0.dist-info/top_level.txt
nmlang-0.1.0.dist-info/RECORD
