Metadata-Version: 2.4
Name: nmlang
Version: 0.1.0
Summary: Numerus - An Esoteric Stack-based Programming Language (Esolang) by TeaserLang
Author-email: Teaserverse <contact@teaserverse.online>
License: Copyright © 2025 Teaserverse
Project-URL: Homepage, https://github.com/TeaserLang/numerus
Project-URL: Bug Tracker, https://github.com/TeaserLang/numerus/issues
Keywords: esolang,stack,numerus,teaserlang
Classifier: Development Status :: 3 - Alpha
Classifier: Intended Audience :: Developers
Classifier: License :: OSI Approved :: MIT License
Classifier: Programming Language :: Python :: 3
Classifier: Programming Language :: Python :: 3.8
Classifier: Programming Language :: Python :: 3.9
Classifier: Programming Language :: Python :: 3.10
Classifier: Programming Language :: Python :: 3.11
Classifier: Topic :: Software Development :: Interpreters
Requires-Python: >=3.8
License-File: LICENSE
Dynamic: license-file
